lnsync_pkg/__init__.py
lnsync_pkg/argparseconfig.py
lnsync_pkg/backtracker.py
lnsync_pkg/blockhash.py
lnsync_pkg/fdupes.py
lnsync_pkg/fileid.py
lnsync_pkg/filetree.py
lnsync_pkg/glob_matcher.py
lnsync_pkg/groupedfileprinter.py
lnsync_pkg/hashtree.py
lnsync_pkg/human2bytes.py
lnsync_pkg/lnsync.py
lnsync_pkg/matcher.py
lnsync_pkg/metadata.py
lnsync_pkg/onegraph.py
lnsync_pkg/onlineoffline.py
lnsync_pkg/onofftype.py
lnsync_pkg/p23compat.py
lnsync_pkg/prefixdbname.py
lnsync_pkg/printutils.py
lnsync_pkg/proptree.py
lnsync_pkg/sqlpropdb.py
random_pkg/__init__.py
random_pkg/random_extras.py
random_pkg/random_tree.py
lnsync-0.5.2.dist-info/LICENSE
lnsync-0.5.2.dist-info/METADATA
lnsync-0.5.2.dist-info/WHEEL
lnsync-0.5.2.dist-info/entry_points.txt
lnsync-0.5.2.dist-info/top_level.txt
lnsync-0.5.2.dist-info/RECORD
