Metadata-Version: 2.1
Name: lnsync
Version: 0.5.2
Summary: Sync by content with hard link support, fast fdupes, and more.
Home-page: https://github.com/mrsimoes/lnsync
Author: Miguel Simoes
Author-email: miguelrsimoes@yahoo.com
License: GNU General Public License v3
Download-URL: https://github.com/mrsimoes/lnsync/archive/v0.5.2.tar.gz
Keywords: sync rsync fast rename backup link hardlink fdupes
Platform: UNKNOWN
Classifier: Development Status :: 3 - Alpha
Classifier: Environment :: Console
Classifier: Operating System :: POSIX :: Linux
Classifier: Programming Language :: Python :: 3.6
Classifier: License :: OSI Approved :: GNU General Public License v3 (GPLv3)
Classifier: Topic :: System :: Archiving :: Backup
Classifier: Topic :: Utilities
Requires-Dist: pyhashxx
Requires-Dist: six
Requires-Dist: psutil
